{"latitude":42.3958,"longitude":-71.1792,"timezone":"America/New_York","offset":-4,"currently":{"time":1414501292,"summary":"Mostly Cloudy","icon":"partly-cloudy-day","nearestStormDistance":11,"nearestStormBearing":291,"precipIntensity":0,"precipProbability":0,"temperature":44.97,"apparentTemperature":44.97,"dewPoint":40.72,"humidity":0.85,"windSpeed":1,"windBearing":151,"visibility":9.18,"cloudCover":0.74,"pressure":1018.34,"ozone":256.76},"minutely":{"summary":"Mostly cloudy for the hour.","icon":"partly-cloudy-day","data":[{"time":1414501260,"precipIntensity":0,"precipProbability":0},{"time":1414501320,"precipIntensity":0,"precipProbability":0},{"time":1414501380,"precipIntensity":0,"precipProbability":0},{"time":1414501440,"precipIntensity":0,"precipProbability":0},{"time":1414501500,"precipIntensity":0,"precipProbability":0},{"time":1414501560,"precipIntensity":0,"precipProbability":0},{"time":1414501620,"precipIntensity":0,"precipProbability":0},{"time":1414501680,"precipIntensity":0,"precipProbability":0},{"time":1414501740,"precipIntensity":0,"precipProbability":0},{"time":1414501800,"precipIntensity":0,"precipProbability":0},{"time":1414501860,"precipIntensity":0,"precipProbability":0},{"time":1414501920,"precipIntensity":0,"precipProbability":0},{"time":1414501980,"precipIntensity":0,"precipProbability":0},{"time":1414502040,"precipIntensity":0,"precipProbability":0},{"time":1414502100,"precipIntensity":0,"precipProbability":0},{"time":1414502160,"precipIntensity":0,"precipProbability":0},{"time":1414502220,"precipIntensity":0,"precipProbability":0},{"time":1414502280,"precipIntensity":0,"precipProbability":0},{"time":1414502340,"precipIntensity":0,"precipProbability":0},{"time":1414502400,"precipIntensity":0,"precipProbability":0},{"time":1414502460,"precipIntensity":0,"precipProbability":0},{"time":1414502520,"precipIntensity":0,"precipProbability":0},{"time":1414502580,"precipIntensity":0,"precipProbability":0},{"time":1414502640,"precipIntensity":0,"precipProbability":0},{"time":1414502700,"precipIntensity":0,"precipProbability":0},{"time":1414502760,"precipIntensity":0,"precipProbability":0},{"time":1414502820,"precipIntensity":0,"precipProbability":0},{"time":1414502880,"precipIntensity":0,"precipProbability":0},{"time":1414502940,"precipIntensity":0,"precipProbability":0},{"time":1414503000,"precipIntensity":0,"precipProbability":0},{"time":1414503060,"precipIntensity":0,"precipProbability":0},{"time":1414503120,"precipIntensity":0,"precipProbability":0},{"time":1414503180,"precipIntensity":0,"precipProbability":0},{"time":1414503240,"precipIntensity":0,"precipProbability":0},{"time":1414503300,"precipIntensity":0,"precipProbability":0},{"time":1414503360,"precipIntensity":0,"precipProbability":0},{"time":1414503420,"precipIntensity":0,"precipProbability":0},{"time":1414503480,"precipIntensity":0,"precipProbability":0},{"time":1414503540,"precipIntensity":0,"precipProbability":0},{"time":1414503600,"precipIntensity":0,"precipProbability":0},{"time":1414503660,"precipIntensity":0,"precipProbability":0},{"time":1414503720,"precipIntensity":0,"precipProbability":0},{"time":1414503780,"precipIntensity":0,"precipProbability":0},{"time":1414503840,"precipIntensity":0,"precipProbability":0},{"time":1414503900,"precipIntensity":0,"precipProbability":0},{"time":1414503960,"precipIntensity":0,"precipProbability":0},{"time":1414504020,"precipIntensity":0,"precipProbability":0},{"time":1414504080,"precipIntensity":0,"precipProbability":0},{"time":1414504140,"precipIntensity":0,"precipProbability":0},{"time":1414504200,"precipIntensity":0,"precipProbability":0},{"time":1414504260,"precipIntensity":0,"precipProbability":0},{"time":1414504320,"precipIntensity":0,"precipProbability":0},{"time":1414504380,"precipIntensity":0,"precipProbability":0},{"time":1414504440,"precipIntensity":0,"precipProbability":0},{"time":1414504500,"precipIntensity":0,"precipProbability":0},{"time":1414504560,"precipIntensity":0,"precipProbability":0},{"time":1414504620,"precipIntensity":0,"precipProbability":0},{"time":1414504680,"precipIntensity":0,"precipProbability":0},{"time":1414504740,"precipIntensity":0,"precipProbability":0},{"time":1414504800,"precipIntensity":0,"precipProbability":0},{"time":1414504860,"precipIntensity":0,"precipProbability":0}]},"hourly":{"summary":"Mostly cloudy throughout the day.","icon":"partly-cloudy-night","data":[{"time":1414501200,"summary":"Mostly Cloudy","icon":"partly-cloudy-day","precipIntensity":0,"precipProbability":0,"temperature":44.85,"apparentTemperature":44.85,"dewPoint":40.68,"humidity":0.85,"windSpeed":0.94,"windBearing":152,"visibility":9.17,"cloudCover":0.73,"pressure":1018.34,"ozone":256.79},{"time":1414504800,"summary":"Mostly Cloudy","icon":"partly-cloudy-day","precipIntensity":0,"precipProbability":0,"temperature":49.56,"apparentTemperature":48.85,"dewPoint":41.89,"humidity":0.75,"windSpeed":3.37,"windBearing":145,"visibility":9.68,"cloudCover":0.75,"pressure":1018.19,"ozone":255.7},{"time":1414508400,"summary":"Mostly Cloudy","icon":"partly-cloudy-day","precipIntensity":0,"precipProbability":0,"temperature":53.6,"apparentTemperature":53.6,"dewPoint":43.01,"humidity":0.67,"windSpeed":5.14,"windBearing":141,"visibility":10,"cloudCover":0.82,"pressure":1017.93,"ozone":254.43},{"time":1414512000,"summary":"Mostly Cloudy","icon":"partly-cloudy-day","precipIntensity":0,"precipProbability":0,"temperature":56.87,"apparentTemperature":56.87,"dewPoint":44.64,"humidity":0.64,"windSpeed":6.49,"windBearing":140,"visibility":10,"cloudCover":0.84,"pressure":1017.5,"ozone":252.77},{"time":1414515600,"summary":"Mostly Cloudy","icon":"partly-cloudy-day","precipIntensity":0,"precipProbability":0,"temperature":60.14,"apparentTemperature":60.14,"dewPoint":46.33,"humidity":0.6,"windSpeed":7.09,"windBearing":147,"visibility":10,"cloudCover":0.81,"pressure":1016.96,"ozone":250.92},{"time":1414519200,"summary":"Mostly Cloudy","icon":"partly-cloudy-day","precipIntensity":0,"precipProbability":0,"temperature":63.47,"apparentTemperature":63.47,"dewPoint":48.46,"humidity":0.58,"windSpeed":7.85,"windBearing":151,"visibility":10,"cloudCover":0.74,"pressure":1016.38,"ozone":249.32},{"time":1414522800,"summary":"Mostly Cloudy","icon":"partly-cloudy-day","precipIntensity":0,"precipProbability":0,"temperature":65.06,"apparentTemperature":65.06,"dewPoint":50.14,"humidity":0.58,"windSpeed":7.98,"windBearing":150,"visibility":10,"cloudCover":0.76,"pressure":1015.78,"ozone":248.21},{"time":1414526400,"summary":"Mostly Cloudy","icon":"partly-cloudy-day","precipIntensity":0,"precipProbability":0,"temperature":64.95,"apparentTemperature":64.95,"dewPoint":51.16,"humidity":0.61,"windSpeed":7.89,"windBearing":153,"visibility":10,"cloudCover":0.84,"pressure":1015.18,"ozone":247.35},{"time":1414530000,"summary":"Mostly Cloudy","icon":"partly-cloudy-day","precipIntensity":0,"precipProbability":0,"temperature":63.71,"apparentTemperature":63.71,"dewPoint":51.72,"humidity":0.65,"windSpeed":7.25,"windBearing":154,"visibility":10,"cloudCover":0.87,"pressure":1014.72,"ozone":246.51},{"time":1414533600,"summary":"Mostly Cloudy","icon":"partly-cloudy-night","precipIntensity":0,"precipProbability":0,"temperature":61.77,"apparentTemperature":61.77,"dewPoint":52.58,"humidity":0.72,"windSpeed":6.64,"windBearing":149,"visibility":10,"cloudCover":0.75,"pressure":1014.49,"ozone":245.5},{"time":1414537200,"summary":"Mostly Cloudy","icon":"partly-cloudy-night","precipIntensity":0,"precipProbability":0,"temperature":60.01,"apparentTemperature":60.01,"dewPoint":53.52,"humidity":0.79,"windSpeed":6.81,"windBearing":152,"visibility":9.69,"cloudCover":0.65,"pressure":1014.4,"ozone":244.5},{"time":1414540800,"summary":"Partly Cloudy","icon":"partly-cloudy-night","precipIntensity":0,"precipProbability":0,"temperature":58.7,"apparentTemperature":58.7,"dewPoint":54.13,"humidity":0.85,"windSpeed":6.97,"windBearing":156,"visibility":9.43,"cloudCover":0.53,"pressure":1014.29,"ozone":243.81},{"time":1414544400,"summary":"Partly Cloudy","icon":"partly-cloudy-night","precipIntensity":0,"precipProbability":0,"temperature":58.05,"apparentTemperature":58.05,"dewPoint":54.4,"humidity":0.88,"windSpeed":6.65,"windBearing":161,"visibility":9.24,"cloudCover":0.59,"pressure":1014.08,"ozone":243.57},{"time":1414548000,"summary":"Mostly Cloudy","icon":"partly-cloudy-night","precipIntensity":0,"precipProbability":0,"temperature":57.66,"apparentTemperature":57.66,"dewPoint":54.84,"humidity":0.9,"windSpeed":6.33,"windBearing":166,"visibility":9.17,"cloudCover":0.69,"pressure":1013.86,"ozone":243.64},{"time":1414551600,"summary":"Mostly Cloudy","icon":"partly-cloudy-night","precipIntensity":0,"precipProbability":0,"temperature":57.39,"apparentTemperature":57.39,"dewPoint":54.8,"humidity":0.91,"windSpeed":6.37,"windBearing":171,"visibility":9.18,"cloudCover":0.86,"pressure":1013.64,"ozone":243.86},{"time":1414555200,"summary":"Overcast","icon":"cloudy","precipIntensity":0,"precipProbability":0,"temperature":57.03,"apparentTemperature":57.03,"dewPoint":54.72,"humidity":0.92,"windSpeed":6.63,"windBearing":174,"visibility":9.19,"cloudCover":0.99,"pressure":1013.41,"ozone":244.24},{"time":1414558800,"summary":"Overcast","icon":"cloudy","precipIntensity":0,"precipProbability":0,"temperature":56.88,"apparentTemperature":56.88,"dewPoint":54.74,"humidity":0.93,"windSpeed":6.74,"windBearing":176,"visibility":9.19,"cloudCover":1,"pressure":1013.16,"ozone":244.77},{"time":1414562400,"summary":"Overcast","icon":"cloudy","precipIntensity":0,"precipProbability":0,"temperature":56.7,"apparentTemperature":56.7,"dewPoint":54.67,"humidity":0.93,"windSpeed":7.11,"windBearing":180,"visibility":8.03,"cloudCover":0.99,"pressure":1012.83,"ozone":245.31},{"time":1414566000,"summary":"Overcast","icon":"cloudy","precipIntensity":0,"precipProbability":0,"temperature":56.63,"apparentTemperature":56.63,"dewPoint":54.84,"humidity":0.94,"windSpeed":7.77,"windBearing":183,"visibility":5.71,"cloudCover":0.99,"pressure":1012.41,"ozone":245.82},{"time":1414569600,"summary":"Overcast","icon":"cloudy","precipIntensity":0,"precipProbability":0,"temperature":56.68,"apparentTemperature":56.68,"dewPoint":55.12,"humidity":0.95,"windSpeed":8.73,"windBearing":185,"visibility":5.59,"cloudCover":0.99,"pressure":1011.94,"ozone":246.35},{"time":1414573200,"summary":"Overcast","icon":"cloudy","precipIntensity":0,"precipProbability":0,"temperature":56.91,"apparentTemperature":56.91,"dewPoint":55.25,"humidity":0.94,"windSpeed":9.11,"windBearing":187,"visibility":5.06,"cloudCover":0.98,"pressure":1011.53,"ozone":246.82},{"time":1414576800,"summary":"Overcast","icon":"cloudy","precipIntensity":0,"precipProbability":0,"temperature":56.86,"apparentTemperature":56.86,"dewPoint":55.19,"humidity":0.94,"windSpeed":9.14,"windBearing":191,"visibility":3.83,"cloudCover":0.98,"pressure":1011.35,"ozone":247.18},{"time":1414580400,"summary":"Overcast","icon":"cloudy","precipIntensity":0,"precipProbability":0,"temperature":57,"apparentTemperature":57,"dewPoint":55.28,"humidity":0.94,"windSpeed":8.43,"windBearing":193,"visibility":3.85,"cloudCover":0.99,"pressure":1011.28,"ozone":247.5},{"time":1414584000,"summary":"Overcast","icon":"cloudy","precipIntensity":0,"precipProbability":0,"temperature":57.73,"apparentTemperature":57.73,"dewPoint":55.54,"humidity":0.92,"windSpeed":8.08,"windBearing":194,"visibility":3.88,"cloudCover":0.99,"pressure":1011.14,"ozone":247.86},{"time":1414587600,"summary":"Overcast","icon":"cloudy","precipIntensity":0,"precipProbability":0,"temperature":59.5,"apparentTemperature":59.5,"dewPoint":56.51,"humidity":0.9,"windSpeed":8.44,"windBearing":194,"visibility":6.15,"cloudCover":0.99,"pressure":1010.91,"ozone":248.25},{"time":1414591200,"summary":"Overcast","icon":"cloudy","precipIntensity":0,"precipProbability":0,"temperature":61.76,"apparentTemperature":61.76,"dewPoint":57.39,"humidity":0.86,"windSpeed":9.07,"windBearing":195,"visibility":7.53,"cloudCover":0.99,"pressure":1010.62,"ozone":248.69},{"time":1414594800,"summary":"Overcast","icon":"cloudy","precipIntensity":0,"precipProbability":0,"temperature":63.82,"apparentTemperature":63.82,"dewPoint":58.08,"humidity":0.82,"windSpeed":9.39,"windBearing":195,"visibility":8.58,"cloudCover":0.99,"pressure":1010.26,"ozone":249.41},{"time":1414598400,"summary":"Overcast","icon":"cloudy","precipIntensity":0,"precipProbability":0,"temperature":65.51,"apparentTemperature":65.51,"dewPoint":58.64,"humidity":0.79,"windSpeed":9.25,"windBearing":196,"visibility":9.4,"cloudCover":0.99,"pressure":1009.76,"ozone":250.72},{"time":1414602000,"summary":"Overcast","icon":"cloudy","precipIntensity":0,"precipProbability":0,"temperature":67.13,"apparentTemperature":67.13,"dewPoint":59.34,"humidity":0.76,"windSpeed":8.7,"windBearing":198,"visibility":9.93,"cloudCover":0.99,"pressure":1009.19,"ozone":252.31},{"time":1414605600,"summary":"Overcast","icon":"cloudy","precipIntensity":0.004,"precipProbability":0.09,"precipType":"rain","temperature":69.12,"apparentTemperature":69.12,"dewPoint":60.94,"humidity":0.75,"windSpeed":7.93,"windBearing":202,"visibility":9.95,"cloudCover":0.99,"pressure":1008.74,"ozone":253.41},{"time":1414609200,"summary":"Light Rain","icon":"rain","precipIntensity":0.0342,"precipProbability":0.31,"precipType":"rain","temperature":68.56,"apparentTemperature":68.56,"dewPoint":61.13,"humidity":0.77,"windSpeed":6.97,"windBearing":209,"visibility":8.24,"cloudCover":0.98,"pressure":1008.48,"ozone":253.39},{"time":1414612800,"summary":"Rain","icon":"rain","precipIntensity":0.0713,"precipProbability":0.43,"precipType":"rain","temperature":67.12,"apparentTemperature":67.12,"dewPoint":61.02,"humidity":0.81,"windSpeed":6.42,"windBearing":222,"visibility":5.97,"cloudCover":0.98,"pressure":1008.38,"ozone":252.89},{"time":1414616400,"summary":"Rain","icon":"rain","precipIntensity":0.0898,"precipProbability":0.52,"precipType":"rain","temperature":65.38,"apparentTemperature":65.38,"dewPoint":60.44,"humidity":0.84,"windSpeed":6.48,"windBearing":239,"visibility":4.84,"cloudCover":0.97,"pressure":1008.39,"ozone":253.07},{"time":1414620000,"summary":"Rain","icon":"rain","precipIntensity":0.0756,"precipProbability":0.59,"precipType":"rain","temperature":63.67,"apparentTemperature":63.67,"dewPoint":59.57,"humidity":0.87,"windSpeed":6.35,"windBearing":252,"visibility":5.99,"cloudCover":0.97,"pressure":1008.57,"ozone":254.5},{"time":1414623600,"summary":"Light Rain","icon":"rain","precipIntensity":0.0426,"precipProbability":0.66,"precipType":"rain","temperature":61.95,"apparentTemperature":61.95,"dewPoint":58.52,"humidity":0.89,"windSpeed":6.04,"windBearing":265,"visibility":8.28,"cloudCover":0.98,"pressure":1008.89,"ozone":256.62},{"time":1414627200,"summary":"Light Rain","icon":"rain","precipIntensity":0.0146,"precipProbability":0.65,"precipType":"rain","temperature":60.31,"apparentTemperature":60.31,"dewPoint":57.18,"humidity":0.89,"windSpeed":6.19,"windBearing":276,"visibility":10,"cloudCover":0.99,"pressure":1009.23,"ozone":258.84},{"time":1414630800,"summary":"Drizzle","icon":"rain","precipIntensity":0.0067,"precipProbability":0.45,"precipType":"rain","temperature":58.88,"apparentTemperature":58.88,"dewPoint":55.58,"humidity":0.89,"windSpeed":6.62,"windBearing":285,"visibility":10,"cloudCover":0.99,"pressure":1009.56,"ozone":261.15},{"time":1414634400,"summary":"Drizzle","icon":"rain","precipIntensity":0.0073,"precipProbability":0.45,"precipType":"rain","temperature":57.55,"apparentTemperature":57.55,"dewPoint":53.74,"humidity":0.87,"windSpeed":7.03,"windBearing":290,"visibility":10,"cloudCover":1,"pressure":1009.92,"ozone":263.57},{"time":1414638000,"summary":"Drizzle","icon":"rain","precipIntensity":0.0079,"precipProbability":0.43,"precipType":"rain","temperature":56.2,"apparentTemperature":56.2,"dewPoint":51.73,"humidity":0.85,"windSpeed":7.41,"windBearing":292,"visibility":10,"cloudCover":1,"pressure":1010.25,"ozone":265.49},{"time":1414641600,"summary":"Drizzle","icon":"rain","precipIntensity":0.0056,"precipProbability":0.22,"precipType":"rain","temperature":54.75,"apparentTemperature":54.75,"dewPoint":49.41,"humidity":0.82,"windSpeed":7.86,"windBearing":291,"visibility":10,"cloudCover":1,"pressure":1010.51,"ozone":266.47},{"time":1414645200,"summary":"Overcast","icon":"cloudy","precipIntensity":0.0033,"precipProbability":0.06,"precipType":"rain","temperature":53.32,"apparentTemperature":53.32,"dewPoint":46.97,"humidity":0.79,"windSpeed":8.28,"windBearing":290,"visibility":10,"cloudCover":0.99,"pressure":1010.72,"ozone":266.97},{"time":1414648800,"summary":"Overcast","icon":"cloudy","precipIntensity":0.0016,"precipProbability":0.01,"precipType":"rain","temperature":52.11,"apparentTemperature":52.11,"dewPoint":45.02,"humidity":0.77,"windSpeed":8.36,"windBearing":288,"visibility":10,"cloudCover":0.98,"pressure":1010.87,"ozone":267.74},{"time":1414652400,"summary":"Overcast","icon":"cloudy","precipIntensity":0,"precipProbability":0,"temperature":51.19,"apparentTemperature":51.19,"dewPoint":43.91,"humidity":0.76,"windSpeed":7.88,"windBearing":285,"visibility":10,"cloudCover":0.98,"pressure":1010.91,"ozone":269.01},{"time":1414656000,"summary":"Overcast","icon":"cloudy","precipIntensity":0,"precipProbability":0,"temperature":50.39,"apparentTemperature":50.39,"dewPoint":43.23,"humidity":0.76,"windSpeed":7.35,"windBearing":280,"visibility":10,"cloudCover":0.97,"pressure":1010.94,"ozone":270.57},{"time":1414659600,"summary":"Mostly Cloudy","icon":"partly-cloudy-night","precipIntensity":0,"precipProbability":0,"temperature":49.55,"apparentTemperature":46.6,"dewPoint":42.64,"humidity":0.77,"windSpeed":7.09,"windBearing":276,"visibility":10,"cloudCover":0.93,"pressure":1011.11,"ozone":272.52},{"time":1414663200,"summary":"Mostly Cloudy","icon":"partly-cloudy-night","precipIntensity":0,"precipProbability":0,"temperature":48.38,"apparentTemperature":45.19,"dewPoint":42.02,"humidity":0.79,"windSpeed":7.1,"windBearing":274,"visibility":10,"cloudCover":0.85,"pressure":1011.56,"ozone":275.34},{"time":1414666800,"summary":"Mostly Cloudy","icon":"partly-cloudy-night","precipIntensity":0,"precipProbability":0,"temperature":47.17,"apparentTemperature":43.66,"dewPoint":41.46,"humidity":0.8,"windSpeed":7.25,"windBearing":274,"visibility":10,"cloudCover":0.73,"pressure":1012.21,"ozone":278.56},{"time":1414670400,"summary":"Mostly Cloudy","icon":"partly-cloudy-day","precipIntensity":0,"precipProbability":0,"temperature":46.85,"apparentTemperature":43.18,"dewPoint":41.16,"humidity":0.8,"windSpeed":7.44,"windBearing":276,"visibility":10,"cloudCover":0.6,"pressure":1012.73,"ozone":280.93},{"time":1414674000,"summary":"Partly Cloudy","icon":"partly-cloudy-day","precipIntensity":0,"precipProbability":0,"temperature":47.9,"apparentTemperature":44.33,"dewPoint":41.12,"humidity":0.77,"windSpeed":7.72,"windBearing":281,"visibility":10,"cloudCover":0.42,"pressure":1013.06,"ozone":281.81}]},"daily":{"summary":"Light rain tomorrow through Sunday, with temperatures falling to 45°F on Sunday.","icon":"rain","data":[{"time":1414468800,"summary":"Mostly cloudy throughout the day.","icon":"partly-cloudy-day","sunriseTime":1414494858,"sunsetTime":1414532705,"moonPhase":0.16,"precipIntensity":0,"precipIntensityMax":0,"precipProbability":0,"temperatureMin":40.23,"temperatureMinTime":1414490400,"temperatureMax":65.06,"temperatureMaxTime":1414522800,"apparentTemperatureMin":40.23,"apparentTemperatureMinTime":1414490400,"apparentTemperatureMax":65.06,"apparentTemperatureMaxTime":1414522800,"dewPoint":45.37,"humidity":0.78,"windSpeed":3.92,"windBearing":155,"visibility":9.25,"cloudCover":0.62,"pressure":1016.54,"ozone":253.82},{"time":1414555200,"summary":"Rain starting in the afternoon.","icon":"rain","sunriseTime":1414581333,"sunsetTime":1414619023,"moonPhase":0.2,"precipIntensity":0.0145,"precipIntensityMax":0.0898,"precipIntensityMaxTime":1414616400,"precipProbability":0.66,"precipType":"rain","temperatureMin":56.2,"temperatureMinTime":1414638000,"temperatureMax":69.12,"temperatureMaxTime":1414605600,"apparentTemperatureMin":56.2,"apparentTemperatureMinTime":1414638000,"apparentTemperatureMax":69.12,"apparentTemperatureMaxTime":1414605600,"dewPoint":56.88,"humidity":0.87,"windSpeed":6.24,"windBearing":209,"visibility":7.49,"cloudCover":0.99,"pressure":1010.42,"ozone":251.59},{"time":1414641600,"summary":"Mostly cloudy in the morning.","icon":"partly-cloudy-night","sunriseTime":1414667808,"sunsetTime":1414705343,"moonPhase":0.24,"precipIntensity":0.0006,"precipIntensityMax":0.0056,"precipIntensityMaxTime":1414641600,"precipProbability":0.22,"precipType":"rain","temperatureMin":46.85,"temperatureMinTime":1414670400,"temperatureMax":55.05,"temperatureMaxTime":1414695600,"apparentTemperatureMin":43.18,"apparentTemperatureMinTime":1414670400,"apparentTemperatureMax":55.05,"apparentTemperatureMaxTime":1414695600,"dewPoint":41.88,"humidity":0.7,"windSpeed":6.81,"windBearing":285,"visibility":10,"cloudCover":0.51,"pressure":1012.68,"ozone":276.79},{"time":1414728000,"summary":"Mostly cloudy throughout the day.","icon":"partly-cloudy-day","sunriseTime":1414754283,"sunsetTime":1414791664,"moonPhase":0.27,"precipIntensity":0,"precipIntensityMax":0,"precipProbability":0,"temperatureMin":41.81,"temperatureMinTime":1414753200,"temperatureMax":51.59,"temperatureMaxTime":1414785600,"apparentTemperatureMin":37.56,"apparentTemperatureMinTime":1414753200,"apparentTemperatureMax":51.59,"apparentTemperatureMaxTime":1414785600,"dewPoint":39.12,"humidity":0.75,"windSpeed":4.46,"windBearing":354,"visibility":10,"cloudCover":0.68,"pressure":1014.7,"ozone":281.9},{"time":1414814400,"summary":"Drizzle starting in the afternoon.","icon":"rain","sunriseTime":1414840758,"sunsetTime":1414877986,"moonPhase":0.31,"precipIntensity":0.0039,"precipIntensityMax":0.0075,"precipIntensityMaxTime":1414882800,"precipProbability":0.54,"precipType":"rain","temperatureMin":43.65,"temperatureMinTime":1414839600,"temperatureMax":47.28,"temperatureMaxTime":1414861200,"apparentTemperatureMin":37.02,"apparentTemperatureMinTime":1414897200,"apparentTemperatureMax":42.07,"apparentTemperatureMaxTime":1414861200,"dewPoint":39.97,"humidity":0.81,"windSpeed":9.93,"windBearing":1,"cloudCover":0.99,"pressure":1011.73,"ozone":304.03},{"time":1414900800,"summary":"Drizzle in the morning.","icon":"rain","sunriseTime":1414927234,"sunsetTime":1414964310,"moonPhase":0.35,"precipIntensity":0.0047,"precipIntensityMax":0.0083,"precipIntensityMaxTime":1414911600,"precipProbability":0.57,"precipType":"rain","temperatureMin":35.81,"temperatureMinTime":1414987200,"temperatureMax":45.11,"temperatureMaxTime":1414951200,"apparentTemperatureMin":28.41,"apparentTemperatureMinTime":1414987200,"apparentTemperatureMax":38.41,"apparentTemperatureMaxTime":1414951200,"dewPoint":31.91,"humidity":0.7,"windSpeed":13.97,"windBearing":340,"cloudCover":0.75,"pressure":1018.4,"ozone":329.12},{"time":1414990800,"summary":"Mostly cloudy starting in the evening.","icon":"partly-cloudy-night","sunriseTime":1415013709,"sunsetTime":1415050635,"moonPhase":0.39,"precipIntensity":0,"precipIntensityMax":0,"precipProbability":0,"temperatureMin":34.27,"temperatureMinTime":1415008800,"temperatureMax":48.95,"temperatureMaxTime":1415037600,"apparentTemperatureMin":26.66,"apparentTemperatureMinTime":1415008800,"apparentTemperatureMax":45.31,"apparentTemperatureMaxTime":1415037600,"dewPoint":28.63,"humidity":0.63,"windSpeed":7.96,"windBearing":299,"cloudCover":0.09,"pressure":1025.69,"ozone":294.93},{"time":1415077200,"summary":"Mostly cloudy throughout the day.","icon":"partly-cloudy-day","sunriseTime":1415100185,"sunsetTime":1415136962,"moonPhase":0.42,"precipIntensity":0.0015,"precipIntensityMax":0.0027,"precipIntensityMaxTime":1415127600,"precipProbability":0.06,"precipType":"rain","temperatureMin":38.29,"temperatureMinTime":1415091600,"temperatureMax":56.53,"temperatureMaxTime":1415124000,"apparentTemperatureMin":34.05,"apparentTemperatureMinTime":1415095200,"apparentTemperatureMax":56.53,"apparentTemperatureMaxTime":1415124000,"dewPoint":37.71,"humidity":0.69,"windSpeed":8.54,"windBearing":225,"cloudCover":0.87,"pressure":1024.78,"ozone":270.97}]},"flags":{"sources":["nwspa","isd","nearest-precip","fnmoc","sref","rtma","rap","nam","cmc","gfs","madis","lamp","darksky"],"isd-stations":["725059-14702","725059-99999","744900-14702","994971-99999","999999-94701"],"madis-stations":["AP564","AU841","BHBM3","C4655","C6609","C6612","D7355","D8100","D8945","E1024","E2727","E3565","E4331","E5351","E5650","E5913"],"lamp-stations":["KASH","KBED","KBOS","KBVY","KFIT","KLWM","KMHT","KMQE","KORH","KOWD","KSFZ","KTAN"],"darksky-stations":["KBOX"],"units":"us"}}